__init__.py
__main__.py
setup.py
consolidation/__init__.py
consolidation/analyzer.py
consolidation/consolidator.py
consolidation/merger.py
embeddings/__init__.py
embeddings/embeddings.py
embeddings/vector_store.py
lifecycle/__init__.py
lifecycle/evaluator.py
lifecycle/manager.py
lifecycle/policy.py
mcp_server/__init__.py
mcp_server/server.py
mcp_server/tools.py
memory/__init__.py
memory/assistant.py
memory/engine.py
memory/help_guide.py
memory/models.py
memory/state_manager.py
memory/actions/__init__.py
memory/actions/basic.py
memory/actions/consolidate.py
memory/actions/help.py
memory/actions/lifecycle.py
memory/actions/search.py
memory/backup_engine_v1/basic_v2.py
memory/backup_engine_v1/engine.py
memory/backup_engine_v1/search_v2.py
migration/__init__.py
migration/extractors/__init__.py
migration/extractors/checksum_manager.py
migration/extractors/data_validator.py
migration/extractors/secure_extractor.py
migration/orchestrator/__init__.py
migration/orchestrator/parallel_runner.py
migration/orchestrator/phased_migrator.py
migration/orchestrator/rollback_manager.py
migration/security/__init__.py
migration/security/access_control.py
migration/security/data_classifier.py
migration/security/encryption_assessor.py
migration/security/permission_mapper.py
migration/tools/__init__.py
migration/tools/access_controller.py
migration/tools/execution_monitor.py
migration/tools/secure_runner.py
migration/verification/__init__.py
migration/verification/access_verifier.py
migration/verification/data_verifier.py
migration/verification/migration_verifier.py
migration/verification/report_generator.py
migration/verification/security_auditor.py
rag/__init__.py
rag/context.py
rag/pipeline.py
redis/__init__.py
redis/client.py
security/__init__.py
security/access_control.py
security/audit_log.py
security/encryption.py
security/key_manager.py
spark_memory-0.1.2.dist-info/licenses/LICENSE
utils/__init__.py
utils/command_parser.py
utils/config.py
utils/logging.py
utils/time_path.py
spark_memory-0.1.2.dist-info/METADATA
spark_memory-0.1.2.dist-info/WHEEL
spark_memory-0.1.2.dist-info/entry_points.txt
spark_memory-0.1.2.dist-info/top_level.txt
spark_memory-0.1.2.dist-info/RECORD
