Metadata-Version: 2.4
Name: spark-memory
Version: 0.1.2
Summary: High-performance MCP memory server powered by Redis Stack and LangGraph
Author-email: Jason <jaesun23@gmail.com>
License: MIT
Project-URL: Homepage, https://github.com/Jaesun23/spark-memory
Project-URL: Documentation, https://github.com/Jaesun23/spark-memory/blob/main/README.md
Project-URL: Repository, https://github.com/Jaesun23/spark-memory.git
Project-URL: Issues, https://github.com/Jaesun23/spark-memory/issues
Classifier: Development Status :: 4 - Beta
Classifier: Intended Audience :: Developers
Classifier: License :: OSI Approved :: MIT License
Classifier: Programming Language :: Python :: 3
Classifier: Programming Language :: Python :: 3.10
Classifier: Programming Language :: Python :: 3.11
Classifier: Programming Language :: Python :: 3.12
Classifier: Topic :: Software Development :: Libraries :: Python Modules
Classifier: Topic :: Database
Requires-Python: >=3.10
License-File: LICENSE
Requires-Dist: redis[hiredis]>=5.0.0
Requires-Dist: fastmcp>=2.5.1
Requires-Dist: langgraph>=0.1.0
Requires-Dist: pydantic>=2.0.0
Requires-Dist: python-dotenv>=1.0.0
Requires-Dist: cryptography>=41.0.0
Provides-Extra: dev
Requires-Dist: pytest>=8.0.0; extra == "dev"
Requires-Dist: pytest-asyncio>=0.23.0; extra == "dev"
Requires-Dist: pytest-cov>=5.0.0; extra == "dev"
Requires-Dist: black>=24.0.0; extra == "dev"
Requires-Dist: isort>=5.13.0; extra == "dev"
Requires-Dist: flake8>=7.0.0; extra == "dev"
Requires-Dist: mypy>=1.10.0; extra == "dev"
Requires-Dist: pre-commit>=3.7.0; extra == "dev"
Dynamic: license-file
